Metadata-Version: 2.1
Name: notas-musicais-az
Version: 0.1.0
Summary: Notas musicais é um CLI para ajudar na formação de escalas, acordes e campos harmônicos. Baseado no repo do @dunossauro
License: MIT
Author: azmovi
Author-email: azevedoantoniocicero@gmail.com
Requires-Python: >=3.10,<4.0
Classifier: Development Status :: 5 - Production/Stable
Classifier: Environment :: Console
Classifier: License :: OSI Approved :: MIT License
Classifier: Natural Language :: Portuguese (Brazilian)
Classifier: Programming Language :: Python :: 3
Classifier: Programming Language :: Python :: 3.10
Classifier: Programming Language :: Python :: 3.11
Classifier: Programming Language :: Python :: 3.11
Classifier: Topic :: Education
Requires-Dist: rich (>=13.3.2,<14.0.0)
Requires-Dist: typer (>=0.7.0,<0.8.0)
Project-URL: Bug Tracker, https://github.com/azmovi/notas-musicais/issues
Project-URL: Código, https://github.com/azmovi/notas-musicais
Project-URL: Documentação, https://notas-musicais-azevedo.readthedocs.io/pt/latest/
